{
	"credit": "Made with Blockbench",
	"texture_size": [128, 128],
	"textures": {
		"0": "moderntrainparts:block/container_end/black",
		"particle": "moderntrainparts:block/container_end/black"
	},
	"elements": [
		{
			"name": "top_right_back",
			"from": [0, 0, 0],
			"to": [16, 16, 16],
			"faces": {
				"north": {"uv": [6, 2, 8, 4], "texture": "#0"},
				"south": {"uv": [10, 2, 12, 4], "texture": "#0"},
				"west": {"uv": [8, 2, 10, 4], "texture": "#0"},
				"up": {"uv": [12, 8, 14, 10], "rotation": 180, "texture": "#0"}
			}
		}
	]
}